diracengine/__init__.py
diracengine/cmathplus.py
diracengine/constant.py
diracengine/operator.py
diracengine/operatorarray.py
diracengine/state.py
diracengine/wavefunction.py
diracengine-0.0.14.dist-info/LICENSE
diracengine-0.0.14.dist-info/METADATA
diracengine-0.0.14.dist-info/WHEEL
diracengine-0.0.14.dist-info/top_level.txt
diracengine-0.0.14.dist-info/RECORD
