Metadata-Version: 2.1
Name: diracengine
Version: 0.0.14
Summary: The Dirac Quantum Engine
Home-page: UNKNOWN
Author: Nikola Kostadinov
Author-email: <nikolakostadinov@protonmail.com>
License: MIT
Project-URL: Source Code, https://github.com/NikolaKostadinov/diracengine
Keywords: python,quantum,spin,ket,bra,superposition,psi,dirac,engine,schrodinger,pauli,bohr
Platform: UNKNOWN
Classifier: Development Status :: 1 - Planning
Classifier: Intended Audience :: Developers
Classifier: Programming Language :: Python :: 3
Classifier: Environment :: Console
Classifier: Topic :: Scientific/Engineering
Classifier: Topic :: Scientific/Engineering :: Mathematics
Classifier: Topic :: Scientific/Engineering :: Physics
Classifier: Topic :: Scientific/Engineering :: Visualization
Classifier: Operating System :: Unix
Classifier: Operating System :: MacOS :: MacOS X
Classifier: Operating System :: Microsoft :: Windows
License-File: LICENSE
Requires-Dist: numpy
Requires-Dist: matplotlib
Requires-Dist: wheel
